{
    "timestamp": 1728301503,
    "approach_stats": {
        "Начни сообщение с призыва к действию с продуктом.": {
            "failed_checks": {
                "no_word_repetitions": 3,
                "no_contradictions": 2,
                "derived_prepositions": 2
            },
            "total_attempts": 3
        },
        "Начни сообщение с указания на пользу продукта. Используй глагол в побудительном наклонении.": {
            "failed_checks": {
                "synonymous_members": 4,
                "offensive_phrases": 2,
                "no_contradictions": 3,
                "contains_key_message": 1,
                "no_word_repetitions": 1
            },
            "total_attempts": 5
        },
        "Начни сообщение с вопроса, который указывает на пользу продукта для клиента.": {
            "failed_checks": {
                "no_word_repetitions": 5,
                "synonymous_members": 1,
                "no_contradictions": 3,
                "cliches_and_bureaucratese": 1,
                "contains_key_message": 1
            },
            "total_attempts": 7
        }
    }
}